wbgt_aqi_status/__init__.py
wbgt_aqi_status/cli.py
wbgt_aqi_status/core.py
wbgt_aqi_status-0.1.0.dist-info/METADATA
wbgt_aqi_status-0.1.0.dist-info/WHEEL
wbgt_aqi_status-0.1.0.dist-info/entry_points.txt
wbgt_aqi_status-0.1.0.dist-info/licenses/LICENSE
wbgt_aqi_status-0.1.0.dist-info/RECORD
