Metadata-Version: 2.4
Name: wbgt-aqi-status
Version: 0.1.0
Summary: Heat Index + AQI → OK / Modify / Cancel status for practice-day safety.
Author: Elijah Winners
License-File: LICENSE
Keywords: AQI,heat index,practice status,sports safety,student athletes
Classifier: License :: OSI Approved :: MIT License
Classifier: Operating System :: OS Independent
Classifier: Programming Language :: Python :: 3
Requires-Python: >=3.10
Requires-Dist: requests>=2.31
Requires-Dist: tzdata>=2024.1; sys_platform == 'win32'
